aiocleverbot/__init__.py
aiocleverbot/aiocleverbot.py
aiocleverbot-0.1.1.dist-info/LICENSE
aiocleverbot-0.1.1.dist-info/METADATA
aiocleverbot-0.1.1.dist-info/WHEEL
aiocleverbot-0.1.1.dist-info/top_level.txt
aiocleverbot-0.1.1.dist-info/RECORD
