Metadata-Version: 2.1
Name: aiocleverbot
Version: 0.1.1
Summary: Async library for cleverbot
Home-page: https://github.com/johan-naizu/aiocleverbot
Author: Johan Naizu
Author-email: johan@naizu.in
License: UNKNOWN
Project-URL: Bug Tracker, https://github.com/johan-naizu/aiocleverbot/issues
Platform: UNKNOWN
Classifier: Programming Language :: Python :: 3
Classifier: License :: OSI Approved :: MIT License
Classifier: Operating System :: OS Independent
Requires-Python: >=3.6
